{"assets/icons/facebook.png":["assets/icons/facebook.png"],"assets/icons/github.png":["assets/icons/github.png"],"assets/icons/instagram.png":["assets/icons/instagram.png"],"assets/icons/linkedin.png":["assets/icons/linkedin.png"],"assets/icons/logo.png":["assets/icons/logo.png"],"assets/icons/mob_dev.png":["assets/icons/mob_dev.png"],"assets/icons/pen.png":["assets/icons/pen.png"],"assets/icons/twitter.png":["assets/icons/twitter.png"],"assets/icons/web.png":["assets/icons/web.png"],"assets/images/comingsoon.jpg":["assets/images/comingsoon.jpg"]}